efilinglib/__init__.py
efilinglib/archive/__init__.py
efilinglib/archive/aaa.cpython-314-x86_64-linux-gnu.so
efilinglib/archive/check.py
efilinglib/archive/extract.py
efilinglib/archive/handler.cpython-314-x86_64-linux-gnu.so
efilinglib/archive/nnf.cpython-314-x86_64-linux-gnu.so
efilinglib/charset/__init__.py
efilinglib/charset/config.py
efilinglib/charset/convert.py
efilinglib/extract_archive.py
efilinglib/image/__init__.py
efilinglib/image/config.py
efilinglib/image/converter.py
efilinglib/image/funcs.py
efilinglib/image/kind.py
efilinglib/image/results.py
efilinglib/metadata/__init__.py
efilinglib/metadata/generator.py
efilinglib/ocr/__init__.py
efilinglib/ocr/ocr.py
efilinglib/old/info.py
efilinglib/settings/__init__.py
efilinglib/settings/charsets.py
efilinglib/settings/image.py
efilinglib/settings/ocr.py
efilinglib/settings/xml.py
efilinglib/types/code.py
efilinglib/types/ext.py
efilinglib/types/kind.py
efilinglib/xml/__init__.py
efilinglib/xml/config.py
efilinglib/xml/filetypes.py
efilinglib/xml/finder.py
efilinglib/xml/kind.py
efilinglib/xml/merge.py
efilinglib/xml/translate.py
efilinglib/xsl/__init__.py
efilinglib/xsl/finder.py
efilinglib/xsl/stylesheets/__init__.py
efilinglib/xsl/stylesheets/html/__init__.py
efilinglib/xsl/stylesheets/html/abstract.xsl
efilinglib/xsl/stylesheets/html/application.xsl
efilinglib/xsl/stylesheets/html/claims.xsl
efilinglib/xsl/stylesheets/html/common.xsl
efilinglib/xsl/stylesheets/html/cpy-ntc-pat-e-rn.frag.xsl
efilinglib/xsl/stylesheets/html/cpy-ntc-pat-e-rn.xsl
efilinglib/xsl/stylesheets/html/cpy-ntc-pat-e.frag.xsl
efilinglib/xsl/stylesheets/html/cpy-ntc-pat-e.xsl
efilinglib/xsl/stylesheets/html/description.xsl
efilinglib/xsl/stylesheets/html/drawings.xsl
efilinglib/xsl/stylesheets/html/foreign-language-body.abstract.xsl
efilinglib/xsl/stylesheets/html/foreign-language-body.application.xsl
efilinglib/xsl/stylesheets/html/foreign-language-body.claims.xsl
efilinglib/xsl/stylesheets/html/foreign-language-body.description.xsl
efilinglib-0.1.5.dist-info/METADATA
efilinglib-0.1.5.dist-info/WHEEL
efilinglib-0.1.5.dist-info/RECORD
