Metadata-Version: 2.4
Name: efilinglib
Version: 0.1.5
Summary: 
License-Expression: MIT AND (Apache-2.0 OR BSD-2-Clause)
Keywords: example,testpypi,demo
Author: hyperion13th144m
Author-email: hyperion13th144m@gmail.com
Requires-Python: >=3.14
Classifier: Programming Language :: Python :: 3
Classifier: License :: OSI Approved :: MIT License
Classifier: Operating System :: POSIX :: Linux
Requires-Dist: asn1crypto (>=1.5.1,<2.0.0)
